qmlease/__init__.py
qmlease/__main__.py
qmlease/_env.py
qmlease/application/__init__.py
qmlease/application/application.py
qmlease/application/register.py
qmlease/experimental_features/acrylic_window.py
qmlease/experimental_features/win11_mica_material.py
qmlease/pyside/__init__.py
qmlease/pyside/pyside.py
qmlease/pyside/register.py
qmlease/qmlside/__init__.py
qmlease/qmlside/assets.py
qmlease/qmlside/broadcast.py
qmlease/qmlside/console.py
qmlease/qmlside/enum_.py
qmlease/qmlside/hot_reloader/__init__.py
qmlease/qmlside/hot_reloader/hot_reloader.py
qmlease/qmlside/hot_reloader/hot_reloader.qml
qmlease/qmlside/hot_reloader/hot_reloader_legacy.qml
qmlease/qmlside/hot_reloader/watchpaths.py
qmlease/qmlside/js_evaluator.mjs
qmlease/qmlside/js_evaluator.py
qmlease/qmlside/js_evaluator.qml
qmlease/qmlside/layout_engine.py
qmlease/qmlside/layout_helper/__init__.py
qmlease/qmlside/layout_helper/anchors.py
qmlease/qmlside/layout_helper/container_alignment.py
qmlease/qmlside/layout_helper/content_alignment.py
qmlease/qmlside/layout_helper/layout_helper.py
qmlease/qmlside/model/__init__.py
qmlease/qmlside/model/model.py
qmlease/qmlside/model/simple_model.py
qmlease/qmlside/qml_eval.py
qmlease/qmlside/qml_eval.qml
qmlease/qmlside/resource_manager/__init__.py
qmlease/qmlside/resource_manager/assets.py
qmlease/qmlside/resource_manager/base.py
qmlease/qmlside/resource_manager/color.py
qmlease/qmlside/resource_manager/control.py
qmlease/qmlside/resource_manager/layout.py
qmlease/qmlside/resource_manager/motion.py
qmlease/qmlside/resource_manager/shape.py
qmlease/qmlside/resource_manager/text.py
qmlease/qmlside/widgets_backend/__ext__.py
qmlease/qmlside/widgets_backend/__init__.py
qmlease/qmlside/widgets_backend/listview.py
qmlease/qmlside/widgets_backend/logger.py
qmlease/qmlside/widgets_backend/progress.py
qmlease/qmlside/widgets_backend/scope.py
qmlease/qmlside/widgets_backend/slider.py
qmlease/qmlside/widgets_backend/util.py
qmlease/qtcore/__init__.py
qmlease/qtcore/binding.py
qmlease-3.0.4.dist-info/LICENSE
qmlease-3.0.4.dist-info/METADATA
qmlease-3.0.4.dist-info/WHEEL
qmlease-3.0.4.dist-info/RECORD
