Metadata-Version: 2.1
Name: qmlease
Version: 3.0.4
Summary: A flexible toolkit for Python programmer to efficiently develop QML graphical user interface.
Home-page: https://github.com/likianta/qmlease
License: MIT
Author: Likianta
Author-email: likianta@foxmail.com
Requires-Python: >=3.8,<4.0
Classifier: License :: OSI Approved :: MIT License
Classifier: Programming Language :: Python :: 3
Classifier: Programming Language :: Python :: 3.8
Classifier: Programming Language :: Python :: 3.9
Classifier: Programming Language :: Python :: 3.10
Classifier: Programming Language :: Python :: 3.11
Classifier: Programming Language :: Python :: 3.12
Provides-Extra: qt5
Provides-Extra: qt6
Requires-Dist: argsense (>=0.5.6,<0.6.0)
Requires-Dist: lk-logger (>=5.6.4,<6.0.0)
Requires-Dist: lk-utils (>=2.9.0,<3.0.0)
Requires-Dist: pyside2 (>=5.15,<6.0) ; (python_version >= "3.8" and python_version < "3.11") and (extra == "qt5")
Requires-Dist: pyside6 (>=6.4.3,<6.5.0) ; (python_version >= "3.8" and python_version < "3.12") and (extra == "qt6")
Requires-Dist: pyside6 (>=6.6.1,<7.0.0) ; (python_version == "3.12") and (extra == "qt6")
Requires-Dist: qtpy (>=2.3.0,<3.0.0)
Requires-Dist: typing-extensions
Requires-Dist: watchdog (>=3.0.0,<4.0.0) ; python_version >= "3.8" and python_version < "3.12"
